{
  "top_favorable": [
    {
      "country": "United Arab Emirates",
      "iso3": "ARE",
      "region": "Middle East",
      "trend": "improving",
      "summary_en": "The UAE offers one of the most business-friendly regulated environments for exchanges, tokenization and digital asset services, especially in Dubai and ADGM.",
      "summary_pt": "Os Emirados Árabes Unidos oferecem um dos ambientes regulados mais favoráveis a negócios para exchanges, tokenização e serviços com ativos digitais, especialmente em Dubai e ADGM.",
      "last_update": "2026-03-21",
      "criteria": {
        "legal_certainty": 17,
        "proportionality": 13,
        "exchanges": 10,
        "stablecoins": 8,
        "tokenization": 9,
        "taxation": 9,
        "mining_infrastructure": 6,
        "innovation_openness": 10,
        "anti_centralization": 4,
        "defi": 7
      },
      "status": {
        "exchanges": "licensed",
        "stablecoins": "open with rules",
        "tokenization": "very active",
        "taxation": "favorable",
        "mining": "moderate",
        "cbdc": "wholesale and cross-border exploration",
        "defi": "open through regulated touchpoints"
      },
      "laws": [
        "VARA regime",
        "ADGM virtual assets framework"
      ],
      "opportunities_en": [
        "Regional hub",
        "Low-tax environment"
      ],
      "opportunities_pt": [
        "Hub regional",
        "Ambiente de baixa tributação"
      ],
      "risks_en": [
        "Jurisdictional complexity between zones"
      ],
      "risks_pt": [
        "Complexidade jurisdicional entre zonas"
      ],
      "references": [
        {
          "label": "VARA",
          "url": "https://www.vara.ae/"
        }
      ],
      "thesis_core": true,
      "score": 86,
      "classification": "very_favorable",
      "primary_sources": [
        {
          "type": "regulator",
          "title": "VARA rulebooks",
          "authority": "VARA",
          "url": "https://www.vara.ae/en/regulations/",
          "year": 2024
        },
        {
          "type": "policy",
          "title": "UAE virtual assets framework",
          "authority": "Dubai VARA",
          "url": "https://www.vara.ae/en/",
          "year": 2024
        }
      ],
      "authorities": [
        "VARA",
        "ADGM/FSRA as applicable"
      ],
      "defi_focus_en": "The UAE is receptive to digital asset innovation but still channels DeFi exposure through licensed entities and controlled market access points.",
      "defi_focus_pt": "Os Emirados são receptivos à inovação com ativos digitais, mas ainda canalizam a exposição a DeFi por entidades licenciadas e pontos controlados de acesso ao mercado.",
      "defi_signals_en": [
        "Regulated wrappers matter more than protocol purity"
      ],
      "defi_signals_pt": [
        "Estruturas reguladas importam mais que a pureza do protocolo"
      ],
      "profile_quality": "primary_source_backed",
      "normative_act_count": 4
    },
    {
      "country": "Switzerland",
      "iso3": "CHE",
      "region": "Europe",
      "trend": "stable",
      "summary_en": "Switzerland remains one of the strongest jurisdictions for tokenization, DLT trading infrastructure and legal certainty for crypto businesses.",
      "summary_pt": "A Suíça continua sendo uma das jurisdições mais fortes para tokenização, infraestrutura de negociação em DLT e segurança jurídica para negócios cripto.",
      "last_update": "2026-03-26",
      "criteria": {
        "legal_certainty": 18,
        "proportionality": 13,
        "exchanges": 9,
        "stablecoins": 8,
        "tokenization": 10,
        "taxation": 8,
        "mining_infrastructure": 6,
        "innovation_openness": 9,
        "anti_centralization": 4,
        "defi": 8
      },
      "status": {
        "exchanges": "regulated",
        "stablecoins": "open with compliance",
        "tokenization": "highly favorable",
        "taxation": "competitive",
        "mining": "moderate",
        "cbdc": "wholesale focus",
        "defi": "comparatively open with functional analysis"
      },
      "laws": [
        "Swiss DLT Act",
        "FINMA guidance"
      ],
      "opportunities_en": [
        "DLT markets",
        "Custody",
        "Tokenized securities"
      ],
      "opportunities_pt": [
        "Mercados DLT",
        "Custódia",
        "Valores mobiliários tokenizados"
      ],
      "risks_en": [
        "Cost of operation"
      ],
      "risks_pt": [
        "Custo operacional"
      ],
      "references": [
        {
          "label": "Swiss DLT Framework",
          "url": "https://www.sif.admin.ch/"
        }
      ],
      "thesis_core": true,
      "score": 85,
      "classification": "very_favorable",
      "primary_sources": [
        {
          "type": "regulator",
          "title": "FINMA guidance on stablecoins and DLT",
          "authority": "FINMA",
          "url": "https://www.finma.ch/en/news/2024/07/20240726-mm-stablecoins/",
          "year": 2024
        },
        {
          "type": "law",
          "title": "DLT Act framework",
          "authority": "Swiss Confederation",
          "url": "https://www.fedlex.admin.ch/eli/cc/2021/33/en",
          "year": 2021
        }
      ],
      "authorities": [
        "FINMA"
      ],
      "defi_focus_en": "Switzerland offers one of the more functionally sophisticated environments, though DeFi still depends on activity analysis rather than a standalone code.",
      "defi_focus_pt": "A Suíça oferece um dos ambientes funcionalmente mais sofisticados, embora DeFi ainda dependa de análise por atividade e não de um código autônomo.",
      "defi_signals_en": [
        "Functional approach supports innovation with supervision"
      ],
      "defi_signals_pt": [
        "A abordagem funcional apoia inovação com supervisão"
      ],
      "profile_quality": "primary_source_backed",
      "normative_act_count": 4
    },
    {
      "country": "Singapore",
      "iso3": "SGP",
      "region": "Asia",
      "trend": "improving",
      "summary_en": "Singapore combines strict licensing with strong policy support for tokenization, stablecoins and institutional digital asset markets.",
      "summary_pt": "Singapura combina licenciamento rigoroso com forte apoio de política pública para tokenização, stablecoins e mercados institucionais de ativos digitais.",
      "last_update": "2026-03-27",
      "criteria": {
        "legal_certainty": 18,
        "proportionality": 12,
        "exchanges": 8,
        "stablecoins": 9,
        "tokenization": 10,
        "taxation": 8,
        "mining_infrastructure": 4,
        "innovation_openness": 10,
        "anti_centralization": 4,
        "defi": 7
      },
      "status": {
        "exchanges": "licensed",
        "stablecoins": "regulated",
        "tokenization": "very active",
        "taxation": "competitive",
        "mining": "limited",
        "cbdc": "wholesale experimentation",
        "defi": "careful indirect treatment"
      },
      "laws": [
        "Payment Services Act",
        "MAS Stablecoin Framework",
        "Project Guardian"
      ],
      "opportunities_en": [
        "Institutional tokenization",
        "Stablecoins"
      ],
      "opportunities_pt": [
        "Tokenização institucional",
        "Stablecoins"
      ],
      "risks_en": [
        "Strict licensing thresholds"
      ],
      "risks_pt": [
        "Limiares de licenciamento rigorosos"
      ],
      "references": [
        {
          "label": "MAS",
          "url": "https://www.mas.gov.sg/"
        }
      ],
      "thesis_core": true,
      "score": 83,
      "classification": "very_favorable",
      "primary_sources": [
        {
          "type": "law",
          "title": "Payment Services Act",
          "authority": "MAS",
          "url": "https://www.mas.gov.sg/regulation/acts/payment-services-act",
          "year": 2019
        },
        {
          "type": "regulator",
          "title": "MAS Digital Payment Token services",
          "authority": "MAS",
          "url": "https://www.mas.gov.sg/regulation/explainers/payment-services-act",
          "year": 2024
        }
      ],
      "authorities": [
        "MAS"
      ],
      "defi_focus_en": "Singapore distinguishes licensed token services from broader DeFi activity and tends to regulate touchpoints rather than protocols as such.",
      "defi_focus_pt": "Singapura distingue serviços licenciados com tokens da atividade DeFi mais ampla e tende a regular os pontos de contato, não os protocolos em si.",
      "defi_signals_en": [
        "Strong discipline for intermediated access points"
      ],
      "defi_signals_pt": [
        "Disciplina forte para pontos de acesso intermediados"
      ],
      "profile_quality": "primary_source_backed",
      "normative_act_count": 5
    },
    {
      "country": "United States",
      "iso3": "USA",
      "region": "North America",
      "trend": "improving",
      "summary_en": "The United States combines fragmented federal oversight with strong market depth. Stablecoin policy became more structured, but securities-law uncertainty still affects some projects.",
      "summary_pt": "Os Estados Unidos combinam supervisão federal fragmentada com grande profundidade de mercado. A política para stablecoins ficou mais estruturada, mas a incerteza em matéria de valores mobiliários ainda afeta parte dos projetos.",
      "last_update": "2026-03-28",
      "criteria": {
        "legal_certainty": 15,
        "proportionality": 11,
        "exchanges": 7,
        "stablecoins": 8,
        "tokenization": 8,
        "taxation": 7,
        "mining_infrastructure": 9,
        "innovation_openness": 9,
        "anti_centralization": 4,
        "defi": 7
      },
      "status": {
        "exchanges": "regulated with litigation risk",
        "stablecoins": "developing framework",
        "tokenization": "active",
        "taxation": "moderate",
        "mining": "favorable in several states",
        "cbdc": "research only",
        "defi": "active enforcement and indirect treatment"
      },
      "laws": [
        "GENIUS Act (2025)",
        "State-level digital asset laws",
        "Federal agency guidance"
      ],
      "opportunities_en": [
        "Stablecoins",
        "Tokenized capital markets",
        "Mining and compute"
      ],
      "opportunities_pt": [
        "Stablecoins",
        "Mercados de capitais tokenizados",
        "Mineração e computação"
      ],
      "risks_en": [
        "Regulatory fragmentation",
        "Enforcement uncertainty"
      ],
      "risks_pt": [
        "Fragmentação regulatória",
        "Incerteza de enforcement"
      ],
      "references": [
        {
          "label": "White House fact sheet",
          "url": "https://www.whitehouse.gov/"
        }
      ],
      "thesis_core": true,
      "score": 78,
      "classification": "favorable",
      "primary_sources": [
        {
          "type": "regulator",
          "title": "SEC Crypto Assets and Cyber Unit",
          "authority": "SEC",
          "url": "https://www.sec.gov/spotlight/cybersecurity-enforcement-actions",
          "year": 2024
        },
        {
          "type": "regulator",
          "title": "CFTC Digital Assets",
          "authority": "CFTC",
          "url": "https://www.cftc.gov/LearnAndProtect/AdvisoriesAndArticles/DigitalAssets",
          "year": 2024
        },
        {
          "type": "regulator",
          "title": "FinCEN Convertible Virtual Currency guidance",
          "authority": "FinCEN",
          "url": "https://www.fincen.gov/resources/statutes-regulations/guidance/application-fincens-regulations-certain-business-models",
          "year": 2019
        }
      ],
      "authorities": [
        "SEC",
        "CFTC",
        "FinCEN",
        "state regulators"
      ],
      "defi_focus_en": "US DeFi is shaped by enforcement, commodities and securities law, and AML theories applied to interfaces and affiliated actors.",
      "defi_focus_pt": "O DeFi nos EUA é moldado por enforcement, direito de commodities e valores mobiliários e teorias AML aplicadas a interfaces e atores afiliados.",
      "defi_signals_en": [
        "Strong enforcement risk for front ends and promoters",
        "Protocol neutrality remains legally uncertain"
      ],
      "defi_signals_pt": [
        "Alto risco de enforcement para front-ends e promotores",
        "A neutralidade do protocolo permanece juridicamente incerta"
      ],
      "profile_quality": "primary_source_backed",
      "normative_act_count": 6
    },
    {
      "country": "United Kingdom",
      "iso3": "GBR",
      "region": "Europe",
      "trend": "improving",
      "summary_en": "The UK is moving toward a tailored regime for stablecoins, digital securities and broader crypto activities, but implementation remains gradual.",
      "summary_pt": "O Reino Unido caminha para um regime específico para stablecoins, valores mobiliários digitais e atividades cripto em geral, mas a implementação segue gradual.",
      "last_update": "2026-03-20",
      "criteria": {
        "legal_certainty": 16,
        "proportionality": 11,
        "exchanges": 8,
        "stablecoins": 8,
        "tokenization": 8,
        "taxation": 6,
        "mining_infrastructure": 5,
        "innovation_openness": 8,
        "anti_centralization": 4,
        "defi": 6
      },
      "status": {
        "exchanges": "regulated",
        "stablecoins": "developing framework",
        "tokenization": "sandboxing",
        "taxation": "moderate",
        "mining": "neutral",
        "cbdc": "consultation stage",
        "defi": "indirect treatment"
      },
      "laws": [
        "FCA crypto regime",
        "Digital Securities Sandbox"
      ],
      "opportunities_en": [
        "Tokenized securities",
        "Regulatory experimentation"
      ],
      "opportunities_pt": [
        "Valores mobiliários tokenizados",
        "Experimentação regulatória"
      ],
      "risks_en": [
        "Slow implementation"
      ],
      "risks_pt": [
        "Implementação lenta"
      ],
      "references": [
        {
          "label": "Bank of England",
          "url": "https://www.bankofengland.co.uk/"
        }
      ],
      "thesis_core": true,
      "score": 74,
      "classification": "favorable",
      "primary_sources": [
        {
          "type": "regulator",
          "title": "FCA cryptoasset registration regime",
          "authority": "FCA",
          "url": "https://www.fca.org.uk/firms/financial-crime/cryptoassets-registration",
          "year": 2024
        },
        {
          "type": "policy",
          "title": "UK cryptoasset regulatory approach",
          "authority": "HM Treasury",
          "url": "https://www.gov.uk/government/collections/cryptoassets",
          "year": 2024
        }
      ],
      "authorities": [
        "FCA",
        "HM Treasury",
        "Bank of England"
      ],
      "defi_focus_en": "The UK increasingly regulates crypto activity through financial promotions, AML registration and future perimeter reform, but does not yet offer a dedicated DeFi regime.",
      "defi_focus_pt": "O Reino Unido regula crescentemente a atividade cripto por promoções financeiras, registro AML e futura reforma de perímetro, mas ainda não oferece regime dedicado para DeFi.",
      "defi_signals_en": [
        "Front ends and promotions are sensitive regulatory points"
      ],
      "defi_signals_pt": [
        "Front-ends e promoções financeiras são pontos sensíveis"
      ],
      "profile_quality": "primary_source_backed",
      "normative_act_count": 4
    },
    {
      "country": "Canada",
      "iso3": "CAN",
      "region": "North America",
      "trend": "stable",
      "summary_en": "Canada has comparatively strong exchange oversight and mature market institutions, though innovation can face meaningful compliance burdens.",
      "summary_pt": "O Canadá possui supervisão relativamente forte de exchanges e instituições de mercado maduras, embora a inovação possa enfrentar ônus relevantes de compliance.",
      "last_update": "2026-03-09",
      "criteria": {
        "legal_certainty": 15,
        "proportionality": 10,
        "exchanges": 8,
        "stablecoins": 6,
        "tokenization": 7,
        "taxation": 6,
        "mining_infrastructure": 8,
        "innovation_openness": 7,
        "anti_centralization": 4,
        "defi": 6
      },
      "status": {
        "exchanges": "regulated",
        "stablecoins": "cautious",
        "tokenization": "developing",
        "taxation": "moderate",
        "mining": "favorable in some provinces",
        "cbdc": "research",
        "defi": "indirect treatment"
      },
      "laws": [
        "CSA guidance",
        "FINTRAC rules"
      ],
      "opportunities_en": [
        "Institutional markets",
        "Mining"
      ],
      "opportunities_pt": [
        "Mercados institucionais",
        "Mineração"
      ],
      "risks_en": [
        "Provincial complexity"
      ],
      "risks_pt": [
        "Complexidade provincial"
      ],
      "references": [
        {
          "label": "CSA",
          "url": "https://www.securities-administrators.ca/"
        }
      ],
      "thesis_core": false,
      "score": 71,
      "classification": "favorable",
      "primary_sources": [
        {
          "type": "regulator",
          "title": "FINTRAC virtual currency guidance",
          "authority": "FINTRAC",
          "url": "https://fintrac-canafe.canada.ca/guidance-directives/transaction-operation/lvctr/lvctr-eng",
          "year": 2024
        },
        {
          "type": "regulator",
          "title": "CSA staff notices on crypto assets",
          "authority": "CSA",
          "url": "https://www.securities-administrators.ca/",
          "year": 2024
        }
      ],
      "authorities": [
        "CSA",
        "FINTRAC"
      ],
      "defi_focus_en": "",
      "defi_focus_pt": "",
      "defi_signals_en": [],
      "defi_signals_pt": [],
      "profile_quality": "primary_source_backed",
      "normative_act_count": 4
    },
    {
      "country": "Germany",
      "iso3": "DEU",
      "region": "Europe",
      "trend": "stable",
      "summary_en": "Germany benefits from EU-level legal certainty under MiCA and strong financial regulation, though compliance can be costly.",
      "summary_pt": "A Alemanha se beneficia da segurança jurídica em nível europeu sob o MiCA e de uma forte regulação financeira, embora o compliance possa ser custoso.",
      "last_update": "2026-03-25",
      "criteria": {
        "legal_certainty": 17,
        "proportionality": 10,
        "exchanges": 8,
        "stablecoins": 7,
        "tokenization": 8,
        "taxation": 6,
        "mining_infrastructure": 4,
        "innovation_openness": 7,
        "anti_centralization": 3,
        "defi": 6
      },
      "status": {
        "exchanges": "regulated",
        "stablecoins": "regulated under MiCA",
        "tokenization": "active",
        "taxation": "moderate friction",
        "mining": "limited",
        "cbdc": "euro area exploration",
        "defi": "indirect treatment"
      },
      "laws": [
        "MiCA",
        "German banking supervision rules"
      ],
      "opportunities_en": [
        "Regulated tokenization",
        "Institutional adoption"
      ],
      "opportunities_pt": [
        "Tokenização regulada",
        "Adoção institucional"
      ],
      "risks_en": [
        "High compliance cost"
      ],
      "risks_pt": [
        "Alto custo de compliance"
      ],
      "references": [
        {
          "label": "BaFin",
          "url": "https://www.bafin.de/"
        }
      ],
      "thesis_core": true,
      "score": 70,
      "classification": "favorable",
      "primary_sources": [
        {
          "type": "regulator",
          "title": "BaFin MiCAR portal",
          "authority": "BaFin",
          "url": "https://www.bafin.de/EN/Aufsicht/FinTech/Kryptowerte/MiCAR/micar_node_en.html",
          "year": 2024
        }
      ],
      "authorities": [
        "BaFin"
      ],
      "defi_focus_en": "",
      "defi_focus_pt": "",
      "defi_signals_en": [],
      "defi_signals_pt": [],
      "profile_quality": "primary_source_backed",
      "normative_act_count": 3
    },
    {
      "country": "Japan",
      "iso3": "JPN",
      "region": "Asia",
      "trend": "stable",
      "summary_en": "Japan offers high legal certainty and a mature exchange regime, though compliance remains demanding and innovation can move more slowly.",
      "summary_pt": "O Japão oferece alta segurança jurídica e um regime maduro para exchanges, embora o compliance permaneça exigente e a inovação possa avançar mais lentamente.",
      "last_update": "2026-03-13",
      "criteria": {
        "legal_certainty": 17,
        "proportionality": 10,
        "exchanges": 9,
        "stablecoins": 7,
        "tokenization": 7,
        "taxation": 5,
        "mining_infrastructure": 4,
        "innovation_openness": 7,
        "anti_centralization": 4,
        "defi": 6
      },
      "status": {
        "exchanges": "licensed",
        "stablecoins": "regulated",
        "tokenization": "active",
        "taxation": "moderate friction",
        "mining": "limited",
        "cbdc": "research",
        "defi": "cautious indirect treatment"
      },
      "laws": [
        "Payment Services Act",
        "FSA guidance"
      ],
      "opportunities_en": [
        "Institutional trust",
        "Stablecoins"
      ],
      "opportunities_pt": [
        "Confiança institucional",
        "Stablecoins"
      ],
      "risks_en": [
        "High compliance burden"
      ],
      "risks_pt": [
        "Alto ônus de compliance"
      ],
      "references": [
        {
          "label": "JFSA",
          "url": "https://www.fsa.go.jp/en/"
        }
      ],
      "thesis_core": false,
      "score": 70,
      "classification": "favorable",
      "primary_sources": [
        {
          "type": "law",
          "title": "Payment Services Act",
          "authority": "Japan FSA",
          "url": "https://www.fsa.go.jp/en/refer/acts/index.html",
          "year": 2017
        },
        {
          "type": "regulator",
          "title": "Registered crypto-asset exchange service providers",
          "authority": "Japan FSA",
          "url": "https://www.fsa.go.jp/en/regulated/licensed/en_kasoutuka.pdf",
          "year": 2024
        }
      ],
      "authorities": [
        "Japan FSA"
      ],
      "defi_focus_en": "Japan has mature rules for intermediaries and tokens but remains cautious on DeFi, which is mostly analysed through adjacent categories.",
      "defi_focus_pt": "O Japão possui regras maduras para intermediários e tokens, mas segue cauteloso com DeFi, que é analisado principalmente por categorias adjacentes.",
      "defi_signals_en": [
        "Intermediary clarity exceeds protocol clarity"
      ],
      "defi_signals_pt": [
        "A clareza sobre intermediários supera a clareza sobre protocolos"
      ],
      "profile_quality": "primary_source_backed",
      "normative_act_count": 4
    },
    {
      "country": "Brazil",
      "iso3": "BRA",
      "region": "Latin America",
      "trend": "improving",
      "summary_en": "Brazil has a developing but increasingly structured framework for virtual asset service providers, with progress in prudential oversight but remaining friction in taxation and tokenization.",
      "summary_pt": "O Brasil possui um arcabouço em desenvolvimento, porém cada vez mais estruturado, para prestadores de serviços de ativos virtuais, com avanço na supervisão prudencial, mas ainda com fricções em tributação e tokenização.",
      "last_update": "2026-03-30",
      "criteria": {
        "legal_certainty": 14,
        "proportionality": 10,
        "exchanges": 8,
        "stablecoins": 6,
        "tokenization": 7,
        "taxation": 6,
        "mining_infrastructure": 8,
        "innovation_openness": 7,
        "anti_centralization": 3,
        "defi": 5
      },
      "status": {
        "exchanges": "regulated",
        "stablecoins": "partially open",
        "tokenization": "developing",
        "taxation": "moderate friction",
        "mining": "potentially favorable",
        "cbdc": "pilot under debate",
        "defi": "indirect treatment"
      },
      "laws": [
        "Law 14.478/2022",
        "Decree 11.563/2023",
        "BCB Resolution 520/2025"
      ],
      "opportunities_en": [
        "Tokenization",
        "Green digital infrastructure",
        "Stablecoin development"
      ],
      "opportunities_pt": [
        "Tokenização",
        "Infraestrutura digital verde",
        "Desenvolvimento de stablecoins"
      ],
      "risks_en": [
        "Tax uncertainty",
        "Institutional fragmentation"
      ],
      "risks_pt": [
        "Incerteza tributária",
        "Fragmentação institucional"
      ],
      "references": [
        {
          "label": "Official framework",
          "url": "https://www.planalto.gov.br/"
        }
      ],
      "thesis_core": true,
      "score": 69,
      "classification": "favorable",
      "primary_sources": [
        {
          "type": "law",
          "title": "Lei 14.478/2022",
          "authority": "Congresso Nacional",
          "url": "https://www.planalto.gov.br/ccivil_03/_ato2019-2022/2022/lei/l14478.htm",
          "year": 2022
        },
        {
          "type": "decree",
          "title": "Decreto 11.563/2023",
          "authority": "Presidência da República",
          "url": "https://www.planalto.gov.br/ccivil_03/_ato2023-2026/2023/decreto/d11563.htm",
          "year": 2023
        },
        {
          "type": "regulator",
          "title": "BCB ativos virtuais",
          "authority": "Banco Central do Brasil",
          "url": "https://www.bcb.gov.br/estabilidadefinanceira/criptoativos",
          "year": 2024
        },
        {
          "type": "regulator",
          "title": "CVM orientações sobre criptoativos",
          "authority": "CVM",
          "url": "https://www.gov.br/cvm/pt-br",
          "year": 2024
        }
      ],
      "authorities": [
        "Banco Central do Brasil",
        "CVM",
        "Receita Federal"
      ],
      "defi_focus_en": "Brazil is moving toward clearer regulation of service providers, while DeFi remains mostly treated through indirect legal categories and policy debate.",
      "defi_focus_pt": "O Brasil avança na regulação de prestadores de serviços, enquanto DeFi ainda é tratado sobretudo por categorias jurídicas indiretas e debate regulatório.",
      "defi_signals_en": [
        "No dedicated DeFi statute yet",
        "Likely indirect treatment via VASP, securities and payments law"
      ],
      "defi_signals_pt": [
        "Ainda sem estatuto específico de DeFi",
        "Tratamento provável por VASP, valores mobiliários e pagamentos"
      ],
      "profile_quality": "primary_source_backed",
      "normative_act_count": 7
    },
    {
      "country": "France",
      "iso3": "FRA",
      "region": "Europe",
      "trend": "stable",
      "summary_en": "France combines early digital asset licensing experience with the broader MiCA framework, offering clarity but significant compliance obligations.",
      "summary_pt": "A França combina experiência precoce em licenciamento de ativos digitais com o quadro mais amplo do MiCA, oferecendo clareza, porém com obrigações relevantes de compliance.",
      "last_update": "2026-03-24",
      "criteria": {
        "legal_certainty": 17,
        "proportionality": 9,
        "exchanges": 8,
        "stablecoins": 7,
        "tokenization": 8,
        "taxation": 6,
        "mining_infrastructure": 4,
        "innovation_openness": 7,
        "anti_centralization": 3,
        "defi": 6
      },
      "status": {
        "exchanges": "regulated",
        "stablecoins": "regulated under MiCA",
        "tokenization": "active",
        "taxation": "moderate friction",
        "mining": "limited",
        "cbdc": "euro area exploration",
        "defi": "indirect treatment"
      },
      "laws": [
        "MiCA",
        "PSAN regime"
      ],
      "opportunities_en": [
        "Institutional market entry"
      ],
      "opportunities_pt": [
        "Entrada de mercado institucional"
      ],
      "risks_en": [
        "Regulatory cost"
      ],
      "risks_pt": [
        "Custo regulatório"
      ],
      "references": [
        {
          "label": "AMF France",
          "url": "https://www.amf-france.org/"
        }
      ],
      "thesis_core": true,
      "score": 69,
      "classification": "favorable",
      "primary_sources": [
        {
          "type": "regulator",
          "title": "AMF MiCA transition information",
          "authority": "AMF",
          "url": "https://www.amf-france.org/en/news-publications/news-releases/amf-news-releases/mica-amf-recalls-rules-applicable-psans-during-transition-period",
          "year": 2024
        }
      ],
      "authorities": [
        "AMF"
      ],
      "defi_focus_en": "",
      "defi_focus_pt": "",
      "defi_signals_en": [],
      "defi_signals_pt": [],
      "profile_quality": "primary_source_backed",
      "normative_act_count": 3
    }
  ],
  "top_restrictive": [
    {
      "country": "China",
      "iso3": "CHN",
      "region": "Asia",
      "trend": "stable",
      "summary_en": "China is highly restrictive toward private crypto markets while strongly pursuing state-led digital currency and blockchain infrastructure strategies.",
      "summary_pt": "A China é altamente restritiva em relação aos mercados privados de criptoativos, ao mesmo tempo em que persegue fortemente estratégias estatais de moeda digital e infraestrutura blockchain.",
      "last_update": "2026-03-12",
      "criteria": {
        "legal_certainty": 10,
        "proportionality": 3,
        "exchanges": 1,
        "stablecoins": 1,
        "tokenization": 4,
        "taxation": 5,
        "mining_infrastructure": 1,
        "innovation_openness": 4,
        "anti_centralization": 0,
        "defi": 1
      },
      "status": {
        "exchanges": "banned",
        "stablecoins": "restricted",
        "tokenization": "state-influenced pilots",
        "taxation": "secondary issue",
        "mining": "hostile",
        "cbdc": "advanced state model",
        "defi": "effectively banned"
      },
      "laws": [
        "Crypto trading bans",
        "e-CNY program"
      ],
      "opportunities_en": [
        "Enterprise blockchain under state framework"
      ],
      "opportunities_pt": [
        "Blockchain empresarial sob estrutura estatal"
      ],
      "risks_en": [
        "Severe restrictions",
        "State centralization"
      ],
      "risks_pt": [
        "Restrições severas",
        "Centralização estatal"
      ],
      "references": [
        {
          "label": "PBOC",
          "url": "https://www.pbc.gov.cn/"
        }
      ],
      "thesis_core": true,
      "score": 29,
      "classification": "very_restrictive",
      "primary_sources": [
        {
          "type": "policy",
          "title": "PBOC and agencies notice on virtual currency risks",
          "authority": "PBOC and agencies",
          "url": "http://www.pbc.gov.cn/",
          "year": 2021
        }
      ],
      "authorities": [
        "PBOC and other national authorities"
      ],
      "defi_focus_en": "China treats decentralised crypto-financial activity within a strongly restrictive framework, while supporting state-led digital monetary infrastructure.",
      "defi_focus_pt": "A China trata a atividade cripto-financeira descentralizada dentro de um quadro fortemente restritivo, ao mesmo tempo em que apoia infraestrutura monetária digital liderada pelo Estado.",
      "defi_signals_en": [
        "Very low room for open DeFi markets"
      ],
      "defi_signals_pt": [
        "Espaço muito baixo para mercados DeFi abertos"
      ],
      "profile_quality": "primary_source_backed",
      "normative_act_count": 3
    },
    {
      "country": "India",
      "iso3": "IND",
      "region": "Asia",
      "trend": "mixed",
      "summary_en": "India combines a very large user base with heavy taxation and still-evolving policy, creating a mixed environment for crypto business formation.",
      "summary_pt": "A Índia combina uma base muito grande de usuários com tributação pesada e política ainda em evolução, criando um ambiente misto para a formação de negócios cripto.",
      "last_update": "2026-03-14",
      "criteria": {
        "legal_certainty": 8,
        "proportionality": 4,
        "exchanges": 5,
        "stablecoins": 4,
        "tokenization": 4,
        "taxation": 2,
        "mining_infrastructure": 5,
        "innovation_openness": 6,
        "anti_centralization": 2,
        "defi": 3
      },
      "status": {
        "exchanges": "allowed with friction",
        "stablecoins": "uncertain",
        "tokenization": "limited",
        "taxation": "heavy",
        "mining": "mixed",
        "cbdc": "retail pilot",
        "defi": "tax-heavy uncertain treatment"
      },
      "laws": [
        "Tax provisions",
        "RBI digital rupee pilot"
      ],
      "opportunities_en": [
        "Large domestic market"
      ],
      "opportunities_pt": [
        "Grande mercado doméstico"
      ],
      "risks_en": [
        "Punitive taxation"
      ],
      "risks_pt": [
        "Tributação punitiva"
      ],
      "references": [
        {
          "label": "RBI",
          "url": "https://www.rbi.org.in/"
        }
      ],
      "thesis_core": false,
      "score": 40,
      "classification": "restrictive",
      "primary_sources": [
        {
          "type": "law",
          "title": "Finance Act VDA provisions",
          "authority": "India",
          "url": "https://www.indiabudget.gov.in/doc/Budget2022_23/Finance_Bill.pdf",
          "year": 2022
        }
      ],
      "authorities": [
        "Income Tax Department"
      ],
      "defi_focus_en": "",
      "defi_focus_pt": "",
      "defi_signals_en": [],
      "defi_signals_pt": [],
      "profile_quality": "primary_source_backed",
      "normative_act_count": 3
    },
    {
      "country": "Zimbabwe",
      "iso3": "ZWE",
      "region": "Africa",
      "trend": "mixed",
      "summary_en": "Baseline comparative profile for Zimbabwe. Primary-source regulatory audit is pending deeper country-by-country validation in the Atlas pipeline.",
      "summary_pt": "Perfil comparativo preliminar de Zimbabwe. A auditoria regulatória com fontes primárias ainda depende de validação aprofundada país a país no pipeline do Atlas.",
      "last_update": "2026-04-07",
      "criteria": {
        "legal_certainty": 10,
        "proportionality": 7,
        "exchanges": 4,
        "stablecoins": 4,
        "tokenization": 4,
        "taxation": 4,
        "mining_infrastructure": 4,
        "innovation_openness": 4,
        "anti_centralization": 2,
        "defi": 3
      },
      "status": {
        "exchanges": "uncertain",
        "stablecoins": "uncertain",
        "tokenization": "limited",
        "taxation": "heavy",
        "mining": "allowed with friction",
        "cbdc": "research only",
        "defi": "uncertain"
      },
      "laws": [],
      "opportunities_en": [
        "Expand official-source review",
        "Refine classification by activity",
        "Add tax and AML detail"
      ],
      "opportunities_pt": [
        "Ampliar revisão com fontes oficiais",
        "Refinar classificação por atividade",
        "Adicionar detalhe tributário e AML"
      ],
      "risks_en": [
        "Preliminary profile may change after source audit"
      ],
      "risks_pt": [
        "O perfil preliminar pode mudar após auditoria das fontes"
      ],
      "references": [],
      "score": 43,
      "classification": "restrictive",
      "thesis_core": false,
      "primary_sources": [],
      "authorities": [],
      "defi_focus_en": "",
      "defi_focus_pt": "",
      "defi_signals_en": [],
      "defi_signals_pt": [],
      "profile_quality": "preliminary",
      "normative_act_count": 0
    },
    {
      "country": "Zambia",
      "iso3": "ZMB",
      "region": "Africa",
      "trend": "mixed",
      "summary_en": "Baseline comparative profile for Zambia. Primary-source regulatory audit is pending deeper country-by-country validation in the Atlas pipeline.",
      "summary_pt": "Perfil comparativo preliminar de Zambia. A auditoria regulatória com fontes primárias ainda depende de validação aprofundada país a país no pipeline do Atlas.",
      "last_update": "2026-04-07",
      "criteria": {
        "legal_certainty": 10,
        "proportionality": 7,
        "exchanges": 4,
        "stablecoins": 4,
        "tokenization": 4,
        "taxation": 4,
        "mining_infrastructure": 4,
        "innovation_openness": 4,
        "anti_centralization": 2,
        "defi": 3
      },
      "status": {
        "exchanges": "uncertain",
        "stablecoins": "uncertain",
        "tokenization": "limited",
        "taxation": "heavy",
        "mining": "allowed with friction",
        "cbdc": "research only",
        "defi": "uncertain"
      },
      "laws": [],
      "opportunities_en": [
        "Expand official-source review",
        "Refine classification by activity",
        "Add tax and AML detail"
      ],
      "opportunities_pt": [
        "Ampliar revisão com fontes oficiais",
        "Refinar classificação por atividade",
        "Adicionar detalhe tributário e AML"
      ],
      "risks_en": [
        "Preliminary profile may change after source audit"
      ],
      "risks_pt": [
        "O perfil preliminar pode mudar após auditoria das fontes"
      ],
      "references": [],
      "score": 43,
      "classification": "restrictive",
      "thesis_core": false,
      "primary_sources": [],
      "authorities": [],
      "defi_focus_en": "",
      "defi_focus_pt": "",
      "defi_signals_en": [],
      "defi_signals_pt": [],
      "profile_quality": "preliminary",
      "normative_act_count": 0
    },
    {
      "country": "Uganda",
      "iso3": "UGA",
      "region": "Africa",
      "trend": "mixed",
      "summary_en": "Baseline comparative profile for Uganda. Primary-source regulatory audit is pending deeper country-by-country validation in the Atlas pipeline.",
      "summary_pt": "Perfil comparativo preliminar de Uganda. A auditoria regulatória com fontes primárias ainda depende de validação aprofundada país a país no pipeline do Atlas.",
      "last_update": "2026-04-07",
      "criteria": {
        "legal_certainty": 10,
        "proportionality": 7,
        "exchanges": 4,
        "stablecoins": 4,
        "tokenization": 4,
        "taxation": 4,
        "mining_infrastructure": 4,
        "innovation_openness": 4,
        "anti_centralization": 2,
        "defi": 3
      },
      "status": {
        "exchanges": "uncertain",
        "stablecoins": "uncertain",
        "tokenization": "limited",
        "taxation": "heavy",
        "mining": "allowed with friction",
        "cbdc": "research only",
        "defi": "uncertain"
      },
      "laws": [],
      "opportunities_en": [
        "Expand official-source review",
        "Refine classification by activity",
        "Add tax and AML detail"
      ],
      "opportunities_pt": [
        "Ampliar revisão com fontes oficiais",
        "Refinar classificação por atividade",
        "Adicionar detalhe tributário e AML"
      ],
      "risks_en": [
        "Preliminary profile may change after source audit"
      ],
      "risks_pt": [
        "O perfil preliminar pode mudar após auditoria das fontes"
      ],
      "references": [],
      "score": 43,
      "classification": "restrictive",
      "thesis_core": false,
      "primary_sources": [],
      "authorities": [],
      "defi_focus_en": "",
      "defi_focus_pt": "",
      "defi_signals_en": [],
      "defi_signals_pt": [],
      "profile_quality": "preliminary",
      "normative_act_count": 0
    },
    {
      "country": "Tunisia",
      "iso3": "TUN",
      "region": "Africa",
      "trend": "mixed",
      "summary_en": "Baseline comparative profile for Tunisia. Primary-source regulatory audit is pending deeper country-by-country validation in the Atlas pipeline.",
      "summary_pt": "Perfil comparativo preliminar de Tunisia. A auditoria regulatória com fontes primárias ainda depende de validação aprofundada país a país no pipeline do Atlas.",
      "last_update": "2026-04-07",
      "criteria": {
        "legal_certainty": 10,
        "proportionality": 7,
        "exchanges": 4,
        "stablecoins": 4,
        "tokenization": 4,
        "taxation": 4,
        "mining_infrastructure": 4,
        "innovation_openness": 4,
        "anti_centralization": 2,
        "defi": 3
      },
      "status": {
        "exchanges": "uncertain",
        "stablecoins": "uncertain",
        "tokenization": "limited",
        "taxation": "heavy",
        "mining": "allowed with friction",
        "cbdc": "research only",
        "defi": "uncertain"
      },
      "laws": [],
      "opportunities_en": [
        "Expand official-source review",
        "Refine classification by activity",
        "Add tax and AML detail"
      ],
      "opportunities_pt": [
        "Ampliar revisão com fontes oficiais",
        "Refinar classificação por atividade",
        "Adicionar detalhe tributário e AML"
      ],
      "risks_en": [
        "Preliminary profile may change after source audit"
      ],
      "risks_pt": [
        "O perfil preliminar pode mudar após auditoria das fontes"
      ],
      "references": [],
      "score": 43,
      "classification": "restrictive",
      "thesis_core": false,
      "primary_sources": [],
      "authorities": [],
      "defi_focus_en": "",
      "defi_focus_pt": "",
      "defi_signals_en": [],
      "defi_signals_pt": [],
      "profile_quality": "preliminary",
      "normative_act_count": 0
    },
    {
      "country": "Togo",
      "iso3": "TGO",
      "region": "Africa",
      "trend": "mixed",
      "summary_en": "Baseline comparative profile for Togo. Primary-source regulatory audit is pending deeper country-by-country validation in the Atlas pipeline.",
      "summary_pt": "Perfil comparativo preliminar de Togo. A auditoria regulatória com fontes primárias ainda depende de validação aprofundada país a país no pipeline do Atlas.",
      "last_update": "2026-04-07",
      "criteria": {
        "legal_certainty": 10,
        "proportionality": 7,
        "exchanges": 4,
        "stablecoins": 4,
        "tokenization": 4,
        "taxation": 4,
        "mining_infrastructure": 4,
        "innovation_openness": 4,
        "anti_centralization": 2,
        "defi": 3
      },
      "status": {
        "exchanges": "uncertain",
        "stablecoins": "uncertain",
        "tokenization": "limited",
        "taxation": "heavy",
        "mining": "allowed with friction",
        "cbdc": "research only",
        "defi": "uncertain"
      },
      "laws": [],
      "opportunities_en": [
        "Expand official-source review",
        "Refine classification by activity",
        "Add tax and AML detail"
      ],
      "opportunities_pt": [
        "Ampliar revisão com fontes oficiais",
        "Refinar classificação por atividade",
        "Adicionar detalhe tributário e AML"
      ],
      "risks_en": [
        "Preliminary profile may change after source audit"
      ],
      "risks_pt": [
        "O perfil preliminar pode mudar após auditoria das fontes"
      ],
      "references": [],
      "score": 43,
      "classification": "restrictive",
      "thesis_core": false,
      "primary_sources": [],
      "authorities": [],
      "defi_focus_en": "",
      "defi_focus_pt": "",
      "defi_signals_en": [],
      "defi_signals_pt": [],
      "profile_quality": "preliminary",
      "normative_act_count": 0
    },
    {
      "country": "Tanzania",
      "iso3": "TZA",
      "region": "Africa",
      "trend": "mixed",
      "summary_en": "Baseline comparative profile for Tanzania. Primary-source regulatory audit is pending deeper country-by-country validation in the Atlas pipeline.",
      "summary_pt": "Perfil comparativo preliminar de Tanzania. A auditoria regulatória com fontes primárias ainda depende de validação aprofundada país a país no pipeline do Atlas.",
      "last_update": "2026-04-07",
      "criteria": {
        "legal_certainty": 10,
        "proportionality": 7,
        "exchanges": 4,
        "stablecoins": 4,
        "tokenization": 4,
        "taxation": 4,
        "mining_infrastructure": 4,
        "innovation_openness": 4,
        "anti_centralization": 2,
        "defi": 3
      },
      "status": {
        "exchanges": "uncertain",
        "stablecoins": "uncertain",
        "tokenization": "limited",
        "taxation": "heavy",
        "mining": "allowed with friction",
        "cbdc": "research only",
        "defi": "uncertain"
      },
      "laws": [],
      "opportunities_en": [
        "Expand official-source review",
        "Refine classification by activity",
        "Add tax and AML detail"
      ],
      "opportunities_pt": [
        "Ampliar revisão com fontes oficiais",
        "Refinar classificação por atividade",
        "Adicionar detalhe tributário e AML"
      ],
      "risks_en": [
        "Preliminary profile may change after source audit"
      ],
      "risks_pt": [
        "O perfil preliminar pode mudar após auditoria das fontes"
      ],
      "references": [],
      "score": 43,
      "classification": "restrictive",
      "thesis_core": false,
      "primary_sources": [],
      "authorities": [],
      "defi_focus_en": "",
      "defi_focus_pt": "",
      "defi_signals_en": [],
      "defi_signals_pt": [],
      "profile_quality": "preliminary",
      "normative_act_count": 0
    },
    {
      "country": "Sudan",
      "iso3": "SDN",
      "region": "Africa",
      "trend": "mixed",
      "summary_en": "Baseline comparative profile for Sudan. Primary-source regulatory audit is pending deeper country-by-country validation in the Atlas pipeline.",
      "summary_pt": "Perfil comparativo preliminar de Sudan. A auditoria regulatória com fontes primárias ainda depende de validação aprofundada país a país no pipeline do Atlas.",
      "last_update": "2026-04-07",
      "criteria": {
        "legal_certainty": 10,
        "proportionality": 7,
        "exchanges": 4,
        "stablecoins": 4,
        "tokenization": 4,
        "taxation": 4,
        "mining_infrastructure": 4,
        "innovation_openness": 4,
        "anti_centralization": 2,
        "defi": 3
      },
      "status": {
        "exchanges": "uncertain",
        "stablecoins": "uncertain",
        "tokenization": "limited",
        "taxation": "heavy",
        "mining": "allowed with friction",
        "cbdc": "research only",
        "defi": "uncertain"
      },
      "laws": [],
      "opportunities_en": [
        "Expand official-source review",
        "Refine classification by activity",
        "Add tax and AML detail"
      ],
      "opportunities_pt": [
        "Ampliar revisão com fontes oficiais",
        "Refinar classificação por atividade",
        "Adicionar detalhe tributário e AML"
      ],
      "risks_en": [
        "Preliminary profile may change after source audit"
      ],
      "risks_pt": [
        "O perfil preliminar pode mudar após auditoria das fontes"
      ],
      "references": [],
      "score": 43,
      "classification": "restrictive",
      "thesis_core": false,
      "primary_sources": [],
      "authorities": [],
      "defi_focus_en": "",
      "defi_focus_pt": "",
      "defi_signals_en": [],
      "defi_signals_pt": [],
      "profile_quality": "preliminary",
      "normative_act_count": 0
    },
    {
      "country": "South Sudan",
      "iso3": "SSD",
      "region": "Africa",
      "trend": "mixed",
      "summary_en": "Baseline comparative profile for South Sudan. Primary-source regulatory audit is pending deeper country-by-country validation in the Atlas pipeline.",
      "summary_pt": "Perfil comparativo preliminar de South Sudan. A auditoria regulatória com fontes primárias ainda depende de validação aprofundada país a país no pipeline do Atlas.",
      "last_update": "2026-04-07",
      "criteria": {
        "legal_certainty": 10,
        "proportionality": 7,
        "exchanges": 4,
        "stablecoins": 4,
        "tokenization": 4,
        "taxation": 4,
        "mining_infrastructure": 4,
        "innovation_openness": 4,
        "anti_centralization": 2,
        "defi": 3
      },
      "status": {
        "exchanges": "uncertain",
        "stablecoins": "uncertain",
        "tokenization": "limited",
        "taxation": "heavy",
        "mining": "allowed with friction",
        "cbdc": "research only",
        "defi": "uncertain"
      },
      "laws": [],
      "opportunities_en": [
        "Expand official-source review",
        "Refine classification by activity",
        "Add tax and AML detail"
      ],
      "opportunities_pt": [
        "Ampliar revisão com fontes oficiais",
        "Refinar classificação por atividade",
        "Adicionar detalhe tributário e AML"
      ],
      "risks_en": [
        "Preliminary profile may change after source audit"
      ],
      "risks_pt": [
        "O perfil preliminar pode mudar após auditoria das fontes"
      ],
      "references": [],
      "score": 43,
      "classification": "restrictive",
      "thesis_core": false,
      "primary_sources": [],
      "authorities": [],
      "defi_focus_en": "",
      "defi_focus_pt": "",
      "defi_signals_en": [],
      "defi_signals_pt": [],
      "profile_quality": "preliminary",
      "normative_act_count": 0
    }
  ]
}